another_gitgpt-0.1.1.dist-info/licenses/LICENSE
gitgpt/__init__.py
gitgpt/cli.py
gitgpt/core.py
another_gitgpt-0.1.1.dist-info/METADATA
another_gitgpt-0.1.1.dist-info/WHEEL
another_gitgpt-0.1.1.dist-info/entry_points.txt
another_gitgpt-0.1.1.dist-info/top_level.txt
another_gitgpt-0.1.1.dist-info/RECORD
