Metadata-Version: 2.4
Name: another-gitgpt
Version: 0.1.1
Summary: AI-powered Git commit assistant using GPT and git diff
Author: Nolan Manteufel
Author-email: Nolan Manteufel <nolan@minipcb.com>
License: MIT
Project-URL: Homepage, https://github.com/miniPCB/gitgpt
Project-URL: Repository, https://github.com/miniPCB/gitgpt
Requires-Python: >=3.7
License-File: LICENSE
Requires-Dist: openai>=1.0.0
Dynamic: author
Dynamic: license-file
Dynamic: requires-python
